README.md
privibot/__init__.py
privibot/__main__.py
privibot/callbacks.py
privibot/cli.py
privibot/database.py
privibot/decorators.py
privibot/privileges.py
pyproject.toml
privibot-0.1.1.dist-info/entry_points.txt
privibot-0.1.1.dist-info/LICENSE
privibot-0.1.1.dist-info/WHEEL
privibot-0.1.1.dist-info/METADATA
privibot-0.1.1.dist-info/RECORD
