Metadata-Version: 2.1
Name: privibot
Version: 0.1.1
Summary: A library to build Telegram Bot with a privilege system.
Home-page: https://github.com/pawamoy/privibot
Keywords: telegram-bot
Author: Timothée Mazzucotelli
Author-email: pawamoy@pm.me
Requires-Python: >=3.6,<4.0
Classifier: Programming Language :: Python :: 3
Classifier: Programming Language :: Python :: 3.6
Classifier: Programming Language :: Python :: 3.7
Requires-Dist: python-telegram-bot (==12.0.0b1)
Requires-Dist: sqlalchemy (>=1.3,<2.0)
Project-URL: Repository, https://github.com/pawamoy/privibot
